{"config":{"output_file":null,"full_docs":false,"pub_only":false,"reachable_only":false,"distro_crate":false,"signatures":false,"borrow_data":false},"version":"0.19.1","compilation":{"directory":"c:\\projects_rust\\adder","program":"C:\\Users\\Windows\\.rustup\\toolchains\\stable-x86_64-pc-windows-msvc\\bin\\rls.exe","arguments":[],"output":"c:\\projects_rust\\adder\\target\\rls\\debug\\deps\\libadder-af4e781bcc310451.rmeta"},"prelude":{"crate_id":{"name":"adder","disambiguator":[4693187664217791955,0]},"crate_root":"src","external_crates":[{"file_name":"c:\\projects_rust\\adder\\src\\lib.rs","num":1,"id":{"name":"std","disambiguator":[7379719041391505039,0]}},{"file_name":"c:\\projects_rust\\adder\\src\\lib.rs","num":2,"id":{"name":"core","disambiguator":[5226548339696486402,0]}},{"file_name":"c:\\projects_rust\\adder\\src\\lib.rs","num":3,"id":{"name":"compiler_builtins","disambiguator":[15782588708828798436,0]}},{"file_name":"c:\\projects_rust\\adder\\src\\lib.rs","num":4,"id":{"name":"rustc_std_workspace_core","disambiguator":[11258588358156983047,0]}},{"file_name":"c:\\projects_rust\\adder\\src\\lib.rs","num":5,"id":{"name":"alloc","disambiguator":[6811839233127289238,0]}},{"file_name":"c:\\projects_rust\\adder\\src\\lib.rs","num":6,"id":{"name":"libc","disambiguator":[6798478037195512723,0]}},{"file_name":"c:\\projects_rust\\adder\\src\\lib.rs","num":7,"id":{"name":"unwind","disambiguator":[12572258325454906649,0]}},{"file_name":"c:\\projects_rust\\adder\\src\\lib.rs","num":8,"id":{"name":"cfg_if","disambiguator":[598470195457823820,0]}},{"file_name":"c:\\projects_rust\\adder\\src\\lib.rs","num":9,"id":{"name":"hashbrown","disambiguator":[7285820039251336650,0]}},{"file_name":"c:\\projects_rust\\adder\\src\\lib.rs","num":10,"id":{"name":"rustc_std_workspace_alloc","disambiguator":[15004074270013699283,0]}},{"file_name":"c:\\projects_rust\\adder\\src\\lib.rs","num":11,"id":{"name":"std_detect","disambiguator":[6568562326383462027,0]}},{"file_name":"c:\\projects_rust\\adder\\src\\lib.rs","num":12,"id":{"name":"rustc_demangle","disambiguator":[7532148157145861684,0]}},{"file_name":"c:\\projects_rust\\adder\\src\\lib.rs","num":13,"id":{"name":"panic_unwind","disambiguator":[15660406440960571571,0]}}],"span":{"file_name":"src\\lib.rs","byte_start":0,"byte_end":1259,"line_start":1,"line_end":67,"column_start":1,"column_end":2}},"imports":[],"defs":[{"kind":"Mod","id":{"krate":0,"index":0},"span":{"file_name":"src\\lib.rs","byte_start":0,"byte_end":1259,"line_start":1,"line_end":67,"column_start":1,"column_end":2},"name":"","qualname":"::","value":"src\\lib.rs","parent":null,"children":[{"krate":0,"index":1},{"krate":0,"index":2},{"krate":0,"index":6},{"krate":0,"index":9},{"krate":0,"index":3},{"krate":0,"index":5}],"decl_id":null,"docs":"","sig":null,"attributes":[]},{"kind":"Struct","id":{"krate":0,"index":6},"span":{"file_name":"src\\lib.rs","byte_start":1020,"byte_end":1029,"line_start":54,"line_end":54,"column_start":8,"column_end":17},"name":"Rectangle","qualname":"::Rectangle","value":"Rectangle { _width, _height }","parent":null,"children":[{"krate":0,"index":7},{"krate":0,"index":8}],"decl_id":null,"docs":"","sig":null,"attributes":[]},{"kind":"Field","id":{"krate":0,"index":7},"span":{"file_name":"src\\lib.rs","byte_start":1036,"byte_end":1042,"line_start":55,"line_end":55,"column_start":5,"column_end":11},"name":"_width","qualname":"::Rectangle::_width","value":"u32","parent":{"krate":0,"index":6},"children":[],"decl_id":null,"docs":"","sig":null,"attributes":[]},{"kind":"Field","id":{"krate":0,"index":8},"span":{"file_name":"src\\lib.rs","byte_start":1053,"byte_end":1060,"line_start":56,"line_end":56,"column_start":5,"column_end":12},"name":"_height","qualname":"::Rectangle::_height","value":"u32","parent":{"krate":0,"index":6},"children":[],"decl_id":null,"docs":"","sig":null,"attributes":[]},{"kind":"Local","id":{"krate":0,"index":1073741828},"span":{"file_name":"src\\lib.rs","byte_start":1105,"byte_end":1109,"line_start":60,"line_end":60,"column_start":19,"column_end":23},"name":"self","qualname":"<Rectangle>::_can_hold::self","value":"&Rectangle","parent":null,"children":[],"decl_id":null,"docs":"","sig":null,"attributes":[]},{"kind":"Local","id":{"krate":0,"index":536870916},"span":{"file_name":"src\\lib.rs","byte_start":1111,"byte_end":1116,"line_start":60,"line_end":60,"column_start":25,"column_end":30},"name":"other","qualname":"<Rectangle>::_can_hold::other","value":"&Rectangle","parent":null,"children":[],"decl_id":null,"docs":"","sig":null,"attributes":[]},{"kind":"Method","id":{"krate":0,"index":4},"span":{"file_name":"src\\lib.rs","byte_start":1094,"byte_end":1103,"line_start":60,"line_end":60,"column_start":8,"column_end":17},"name":"_can_hold","qualname":"<Rectangle>::_can_hold","value":"fn _can_hold(&Self, &Rectangle) -> bool","parent":null,"children":[],"decl_id":null,"docs":"","sig":null,"attributes":[]},{"kind":"Local","id":{"krate":0,"index":1073741829},"span":{"file_name":"src\\lib.rs","byte_start":1231,"byte_end":1232,"line_start":65,"line_end":65,"column_start":16,"column_end":17},"name":"a","qualname":"::add_two::a","value":"i32","parent":null,"children":[],"decl_id":null,"docs":"","sig":null,"attributes":[]},{"kind":"Function","id":{"krate":0,"index":5},"span":{"file_name":"src\\lib.rs","byte_start":1223,"byte_end":1230,"line_start":65,"line_end":65,"column_start":8,"column_end":15},"name":"add_two","qualname":"::add_two","value":"pub fn add_two(i32) -> i32","parent":null,"children":[],"decl_id":null,"docs":"","sig":null,"attributes":[]}],"impls":[{"id":0,"kind":"Inherent","span":{"file_name":"src\\lib.rs","byte_start":1075,"byte_end":1084,"line_start":59,"line_end":59,"column_start":6,"column_end":15},"value":"","parent":null,"children":[{"krate":0,"index":4}],"docs":"","sig":null,"attributes":[]}],"refs":[{"kind":"Variable","span":{"file_name":"src\\lib.rs","byte_start":1036,"byte_end":1042,"line_start":55,"line_end":55,"column_start":5,"column_end":11},"ref_id":{"krate":0,"index":7}},{"kind":"Variable","span":{"file_name":"src\\lib.rs","byte_start":1053,"byte_end":1060,"line_start":56,"line_end":56,"column_start":5,"column_end":12},"ref_id":{"krate":0,"index":8}},{"kind":"Type","span":{"file_name":"src\\lib.rs","byte_start":1075,"byte_end":1084,"line_start":59,"line_end":59,"column_start":6,"column_end":15},"ref_id":{"krate":0,"index":6}},{"kind":"Type","span":{"file_name":"src\\lib.rs","byte_start":1119,"byte_end":1128,"line_start":60,"line_end":60,"column_start":33,"column_end":42},"ref_id":{"krate":0,"index":6}},{"kind":"Variable","span":{"file_name":"src\\lib.rs","byte_start":1148,"byte_end":1152,"line_start":61,"line_end":61,"column_start":9,"column_end":13},"ref_id":{"krate":0,"index":1073741828}},{"kind":"Variable","span":{"file_name":"src\\lib.rs","byte_start":1153,"byte_end":1159,"line_start":61,"line_end":61,"column_start":14,"column_end":20},"ref_id":{"krate":0,"index":7}},{"kind":"Variable","span":{"file_name":"src\\lib.rs","byte_start":1162,"byte_end":1167,"line_start":61,"line_end":61,"column_start":23,"column_end":28},"ref_id":{"krate":0,"index":536870916}},{"kind":"Variable","span":{"file_name":"src\\lib.rs","byte_start":1168,"byte_end":1174,"line_start":61,"line_end":61,"column_start":29,"column_end":35},"ref_id":{"krate":0,"index":7}},{"kind":"Variable","span":{"file_name":"src\\lib.rs","byte_start":1178,"byte_end":1182,"line_start":61,"line_end":61,"column_start":39,"column_end":43},"ref_id":{"krate":0,"index":1073741828}},{"kind":"Variable","span":{"file_name":"src\\lib.rs","byte_start":1183,"byte_end":1190,"line_start":61,"line_end":61,"column_start":44,"column_end":51},"ref_id":{"krate":0,"index":8}},{"kind":"Variable","span":{"file_name":"src\\lib.rs","byte_start":1193,"byte_end":1198,"line_start":61,"line_end":61,"column_start":54,"column_end":59},"ref_id":{"krate":0,"index":536870916}},{"kind":"Variable","span":{"file_name":"src\\lib.rs","byte_start":1199,"byte_end":1206,"line_start":61,"line_end":61,"column_start":60,"column_end":67},"ref_id":{"krate":0,"index":8}},{"kind":"Variable","span":{"file_name":"src\\lib.rs","byte_start":1252,"byte_end":1253,"line_start":66,"line_end":66,"column_start":5,"column_end":6},"ref_id":{"krate":0,"index":1073741829}}],"macro_refs":[],"relations":[{"span":{"file_name":"src\\lib.rs","byte_start":1075,"byte_end":1084,"line_start":59,"line_end":59,"column_start":6,"column_end":15},"kind":{"Impl":{"id":0}},"from":{"krate":0,"index":6},"to":{"krate":4294967295,"index":4294967295}}]}